<?xml version="1.0" encoding="utf-8"?>
<myopenmath xmlns:pi="http://pretextbook.org/2020/pretext/internal" id="641982">
<statement>
<p>
Write the equation of the plane shown below:</p>
<p>
<canvas id="plot3d6734df665415d" width="250" height="250" role="img" tabindex="0" aria-label="3D Plot">Not seeing the 3D graph?  <url href="https://www.myopenmath.com/util/mbx.php?id=641982&amp;useflash=true">Try Flash Alternate</url></canvas><fillin characters="20" />  

</p>
</statement>
<solution>
<p><ul><li><m>\displaystyle{z}={3}</m></li></ul></p>
</solution>
</myopenmath>

